bleuio_lib/__init__.py
bleuio_lib/bleuio_funcs.py
bleuio_lib/exceptions.py
bleuio_lib-1.0.1.dist-info/LICENSE.txt
bleuio_lib-1.0.1.dist-info/METADATA
bleuio_lib-1.0.1.dist-info/WHEEL
bleuio_lib-1.0.1.dist-info/top_level.txt
bleuio_lib-1.0.1.dist-info/RECORD
